htsexperimentation/__init__.py
htsexperimentation/compute_results/__init__.py
htsexperimentation/compute_results/results_handler.py
htsexperimentation/compute_results/results_handler_aggregator.py
htsexperimentation/compute_results/results_handler_transformed.py
htsexperimentation/helpers/__init__.py
htsexperimentation/helpers/file_handlers.py
htsexperimentation/helpers/helper_func.py
htsexperimentation/tests/__init__.py
htsexperimentation/tests/test_deepvar_results.py
htsexperimentation/tests/test_plotting_subsampled_fitting.py
htsexperimentation/tests/test_process_transformed_results.py
htsexperimentation/tests/test_results.py
htsexperimentation/tests/test_results_aggregator_samples.py
htsexperimentation/tests/test_results_handler_aggregator.py
htsexperimentation/tests/test_results_m5.py
htsexperimentation/tests/test_results_transformed.py
htsexperimentation/tests/test_sampling_perc.py
htsexperimentation/visualization/__init__.py
htsexperimentation/visualization/plotting.py
htsexperimentation/visualization/plotting_subsampled_fitting.py
htsexperimentation-0.1.72.dist-info/METADATA
htsexperimentation-0.1.72.dist-info/WHEEL
htsexperimentation-0.1.72.dist-info/top_level.txt
htsexperimentation-0.1.72.dist-info/RECORD
