Metadata-Version: 2.1
Name: htsexperimentation
Version: 0.1.72
Summary: Hierarchical time series forecasting package to help analyze experiments
Home-page: UNKNOWN
Author: Luis Roque
Author-email: <roque0luis@gmail.com>
License: UNKNOWN
Keywords: python,time series,hierarchical,forecasting,machine learning
Platform: UNKNOWN
Classifier: Development Status :: 2 - Pre-Alpha
Classifier: Intended Audience :: Science/Research
Classifier: Topic :: Scientific/Engineering
Classifier: Programming Language :: Python :: 3
Classifier: Operating System :: OS Independent
Requires-Dist: setuptools ~=58.0.4
Requires-Dist: tsaugmentation ~=0.5.0
Requires-Dist: pandas ~=1.2.5
Requires-Dist: seaborn ~=0.11.2
Requires-Dist: matplotlib ~=3.3.4
